pychnt/__init__.py
pychnt/instagram.py
pychnt-0.1.dist-info/METADATA
pychnt-0.1.dist-info/WHEEL
pychnt-0.1.dist-info/top_level.txt
pychnt-0.1.dist-info/RECORD
